data_eng_helper/__init__.py
data_eng_helper/analytics.py
data_eng_helper-1.0.5.dist-info/METADATA
data_eng_helper-1.0.5.dist-info/WHEEL
data_eng_helper-1.0.5.dist-info/top_level.txt
data_eng_helper-1.0.5.dist-info/RECORD
