Metadata-Version: 2.1
Name: data-eng-helper
Version: 1.0.5
Summary: data engineers helper module
Home-page: https://github.com/omusana/dataeng_exercise/tree/master/exercise_2
Author: Oscar Musana Asiimwe
Author-email: omusana@gmail.com
License: MIT
Platform: UNKNOWN
Classifier: License :: OSI Approved :: MIT License
Classifier: Programming Language :: Python :: 3
Classifier: Programming Language :: Python :: 3.7
